poe2_tools/__init__.py
poe2_tools/commands.py
poe2_tools/item_parser.py
poe2_tools/main.py
poe2_tools/tooltip.py
poe2_tools-0.1.1.dist-info/LICENSE
poe2_tools-0.1.1.dist-info/METADATA
poe2_tools-0.1.1.dist-info/WHEEL
poe2_tools-0.1.1.dist-info/entry_points.txt
poe2_tools-0.1.1.dist-info/top_level.txt
poe2_tools-0.1.1.dist-info/RECORD
