Metadata-Version: 2.1
Name: poe2-tools
Version: 0.1.1
Summary: A Path of Exile utility tool for item analysis and quick commands
Home-page: https://github.com/whishon/poe2-tools
Author: William Alexander Hishon
Author-email: hishon@live.com
Classifier: Programming Language :: Python :: 3
Classifier: License :: OSI Approved :: MIT License
Classifier: Operating System :: OS Independent
Requires-Python: >=3.7
License-File: LICENSE
Requires-Dist: keyboard>=0.13.5
Requires-Dist: pyperclip>=1.8.2
Requires-Dist: pyautogui>=0.9.53
